weblate/__init__.py
weblate/logger.py
weblate/middleware.py
weblate/models.py
weblate/runner.py
weblate/settings_docker.py
weblate/settings_example.py
weblate/settings_test.py
weblate/settings_test_nose.py
weblate/sitemaps.py
weblate/urls.py
weblate/wsgi.py
weblate/accounts/__init__.py
weblate/accounts/admin.py
weblate/accounts/apps.py
weblate/accounts/auth.py
weblate/accounts/avatar.py
weblate/accounts/captcha.py
weblate/accounts/checks.py
weblate/accounts/data.py
weblate/accounts/forms.py
weblate/accounts/middleware.py
weblate/accounts/models.py
weblate/accounts/notifications.py
weblate/accounts/password_validation.py
weblate/accounts/pipeline.py
weblate/accounts/strategy.py
weblate/accounts/tasks.py
weblate/accounts/urls.py
weblate/accounts/utils.py
weblate/accounts/views.py
weblate/accounts/management/__init__.py
weblate/accounts/management/commands/__init__.py
weblate/accounts/management/commands/dumpuserdata.py
weblate/accounts/management/commands/importuserdata.py
weblate/accounts/migrations/0001_squashed_0019_auto_20200403_2004.py
weblate/accounts/migrations/0002_profile_nearby_strings.py
weblate/accounts/migrations/0003_auto_20200630_1321.py
weblate/accounts/migrations/0004_profile_commented.py
weblate/accounts/migrations/0005_update_comment_count.py
weblate/accounts/migrations/__init__.py
weblate/accounts/templatetags/__init__.py
weblate/accounts/templatetags/authnames.py
weblate/accounts/templatetags/site_url.py
weblate/accounts/tests/__init__.py
weblate/accounts/tests/test_avatars.py
weblate/accounts/tests/test_captcha.py
weblate/accounts/tests/test_commands.py
weblate/accounts/tests/test_middleware.py
weblate/accounts/tests/test_notifications.py
weblate/accounts/tests/test_password_validation.py
weblate/accounts/tests/test_registration.py
weblate/accounts/tests/test_remove.py
weblate/accounts/tests/test_utils.py
weblate/accounts/tests/test_views.py
weblate/addons/__init__.py
weblate/addons/apps.py
weblate/addons/autotranslate.py
weblate/addons/base.py
Weblate_em0t-4.2.dist-info/COPYING
Weblate_em0t-4.2.dist-info/METADATA
Weblate_em0t-4.2.dist-info/WHEEL
Weblate_em0t-4.2.dist-info/entry_points.txt
Weblate_em0t-4.2.dist-info/top_level.txt
Weblate_em0t-4.2.dist-info/RECORD
